{"name":"POST - Create new news without fill title payload","id":"manage-news-admin;post---create-new-news-without-fill-title-payload","testSteps":[{"number":1,"description":"Given I set POST api endpoints manage news admin","duration":349,"startTime":"2023-06-25T16:04:01.349992100+07:00[Asia/Bangkok]","result":"SUCCESS","precondition":false,"level":0,"children":[{"number":2,"description":"I set POST api endpoints manage news admin","duration":3,"startTime":"2023-06-25T16:04:01.689061800+07:00[Asia/Bangkok]","result":"SUCCESS","precondition":false,"level":1}]},{"number":3,"description":"When I send POST HTTP request manage news admin without fill title payload","duration":3656,"startTime":"2023-06-25T16:04:01.702064800+07:00[Asia/Bangkok]","result":"SUCCESS","precondition":false,"level":0,"children":[{"number":4,"description":"I send POST HTTP request manage news admin without fill title payload","duration":3650,"startTime":"2023-06-25T16:04:01.704065500+07:00[Asia/Bangkok]","result":"SUCCESS","precondition":false,"level":1,"children":[{"number":5,"description":"I set POST api endpoints manage news admin","duration":1,"startTime":"2023-06-25T16:04:03.242868700+07:00[Asia/Bangkok]","result":"SUCCESS","precondition":false,"level":2},{"number":6,"description":"POST https://sociops-backend-production.up.railway.app/news","duration":0,"startTime":"2023-06-25T16:04:05.302369+07:00[Asia/Bangkok]","result":"SUCCESS","restQuery":{"method":"POST","path":"https://sociops-backend-production.up.railway.app/news","content":"{\n    \"description\": \"andira2 - Proin et euismod diam. Duis fermentum felis nisi\",\n    \"title\": \"\"\n}","contentType":"application/json","requestHeaders":"Authorization\u003dBearer eyJhbGciOiJIUzI1NiIsInR5cCI6IkpXVCJ9.eyJpZCI6IjUiLCJuYW1lIjoiUGFrIEpvaG4iLCJyb2xlIjoiQURNSU4iLCJleHAiOjE2ODc3MjY5ODN9.7WfpfZfxsKIkLfL6maSf_3OEpiciuAJMsuNYpUH0i90\r\n\t\t\t\tAccept\u003d*/*\r\n\t\t\t\tContent-Type\u003dapplication/json","requestCookies":"","responseHeaders":"content-type: application/json; charset\u003dUTF-8\r\nvary: Origin\r\ndate: Sun, 25 Jun 2023 09:04:09 GMT\r\ncontent-length: 89\r\nserver: railway\r","responseCookies":"\r","responseBody":"{\n    \"data\": [\n        \"Title is a required field\"\n    ],\n    \"message\": \"ERROR_INPUT_VALIDATION\",\n    \"status\": false\n}","statusCode":400},"precondition":false,"level":2}]}]},{"number":7,"description":"Then I receive HTTP response code 400 manage news admin","duration":12,"startTime":"2023-06-25T16:04:05.362953900+07:00[Asia/Bangkok]","result":"SUCCESS","precondition":false,"level":0,"children":[{"number":8,"description":"I receive HTTP response code 400 manage news admin","duration":4,"startTime":"2023-06-25T16:04:05.366418500+07:00[Asia/Bangkok]","result":"SUCCESS","precondition":false,"level":1}]}],"userStory":{"id":"manage-news-admin","storyName":"Manage News Admin","displayName":"Manage News Admin","path":"adminManageNews.feature","narrative":"    As an admin\n    I want to manage news\n    So that I can create and read news  ","type":"feature","qualifiedTag":{"name":"Manage News Admin","type":"feature","displayName":"Manage News Admin"}},"featureTag":{"name":"Manage News Admin","type":"feature","displayName":"Manage News Admin"},"title":"POST - Create new news without fill title payload","description":"","tags":[{"name":"Windows","type":"context","displayName":"Windows"},{"name":"Manage News Admin","type":"feature","displayName":"Manage News Admin"}],"allTags":[{"name":"Windows","type":"context","displayName":"Windows"},{"name":"Manage News Admin","type":"feature","displayName":"Manage News Admin"}],"startTime":"2023-06-25T16:04:01.237760+07:00[Asia/Bangkok]","duration":4142,"projectKey":"","isManualTestingUpToDate":false,"context":"windows","manual":false,"testSource":"Cucumber","result":"SUCCESS"}